manual/__init__.py
manual/base.py
manual/util.py
manual-0.0.2.dist-info/LICENSE
manual-0.0.2.dist-info/METADATA
manual-0.0.2.dist-info/WHEEL
manual-0.0.2.dist-info/top_level.txt
manual-0.0.2.dist-info/RECORD
