Metadata-Version: 2.1
Name: manual
Version: 0.0.2
Summary: Python interfaces to system calls
Home-page: https://github.com/thorwhalen/manual
Author: Thor Whalen
License: apache-2.0
Platform: any
License-File: LICENSE
Requires-Dist: i2
